README.md
setup.cfg
setup.py
language_detector/__init__.py
language_detector.egg-info/PKG-INFO
language_detector.egg-info/SOURCES.txt
language_detector.egg-info/dependency_links.txt
language_detector.egg-info/top_level.txt
language_detector/prep/char_language.txt
language_detector/tests/__init__.py
language_detector/tests/test.py