Metadata-Version: 2.1
Name: language-detector
Version: 5.0.1
Summary: Detect language of text
Home-page: https://github.com/DanielJDufour/language-detector
Author: Daniel J. Dufour
Author-email: daniel.j.dufour@gmail.com
License: UNKNOWN
Download-URL: https://github.com/DanielJDufour/language-detector/tarball/download
Keywords: arabic,farsi,french,kurdish,kurmanci,language,nlp,python,sorani,spanish,tagging,turkish
Platform: UNKNOWN
Classifier: Development Status :: 5 - Production/Stable
Classifier: Programming Language :: Python :: 2
Classifier: Programming Language :: Python :: 3
Classifier: License :: OSI Approved :: Apache Software License
Classifier: Operating System :: OS Independent
